[
    {
        "cateid": "c1",
        "catename": "Cate 1"
    },
    {
        "cateid": "c2",
        "catename": "Cate 2"
    },
    {
        "cateid": "c3",
        "catename": "Cate 3"
    },
    {
        "cateid": "c4",
        "catename": "Cate 4"
    },
    {
        "cateid": "c5",
        "catename": "Cate 5"
    },
    {
        "cateid": "c6",
        "catename": "Cate 6"
    },
    {
        "cateid": "c7",
        "catename": "Cate 7"
    },
    {
        "cateid": "c8",
        "catename": "Cate 8"
    },
    {
        "cateid": "c9",
        "catename": "Cate 9"
    },
    {
        "cateid": "c10",
        "catename": "Cate 10"
    },
    {
        "cateid": "c11",
        "catename": "Cate 11"
    },
    {
        "cateid": "c12",
        "catename": "Cate 12"
    },
    {
        "cateid": "c13",
        "catename": "Cate 13"
    },
    {
        "cateid": "c14",
        "catename": "Cate 14"
    },
    {
        "cateid": "c15",
        "catename": "Cate 15"
    },
    {
        "cateid": "c16",
        "catename": "Cate 16"
    },
    {
        "cateid": "c17",
        "catename": "Cate 17"
    },
    {
        "cateid": "c18",
        "catename": "Cate 18"
    },
    {
        "cateid": "c19",
        "catename": "Cate 19"
    },
    {
        "cateid": "c20",
        "catename": "Cate 20"
    }
]